PROGRAMS/verilog/COA/Assignment1/Assignment1COA-master/Q2/decoder/decoder.v
/**
*	Module for 4:16 decoder
*	By: Omkar Prabhu 16CO233
*	13th October 2017
*/

module decoder (output reg [0:15] out, input [0:3] in);

	// thread to decode input
	always @ (in) begin
		// check which input and give corresponding output
		case (in) 
			4'b0000 : out = 16'b0000000000000001; 
			4'b0001 : out = 16'b0000000000000010; 
			4'b0010 : out = 16'b0000000000000100; 
			4'b0011 : out = 16'b0000000000001000; 
			4'b0100 : out = 16'b0000000000010000; 
			4'b0101 : out = 16'b0000000000100000; 
			4'b0110 : out = 16'b0000000001000000; 
			4'b0111 : out = 16'b0000000010000000; 
			4'b1000 : out = 16'b0000000100000000; 
			4'b1001 : out = 16'b0000001000000000; 
			4'b1010 : out = 16'b0000010000000000; 
			4'b1011 : out = 16'b0000100000000000; 
			4'b1100 : out = 16'b0001000000000000; 
			4'b1101 : out = 16'b0010000000000000; 
			4'b1110 : out = 16'b0100000000000000; 
			4'b1111 : out = 16'b1000000000000000;
			default: out = 16'b0000000000000000; 
		endcase
		
	end


endmodule

PROGRAMS/verilog/COA/Assignment1/Assignment1COA-master/Q2/decoder/t_decoder.v
/**
*	Test bench for 4:16 decoder
*	By: Omkar Prabhu 16CO233
*	13th October 2017
*/

`timescale 1ns/100ps

module t_decoder;

	// output 
	wire [0:15] out;
	// input 
	reg [0:3] in;
	
	// decoder thread instantiated
	decoder inst (out, in);
	
	// check for various input combinations
	initial begin
	
		$dumpfile("decoder.vcd");
		$dumpvars(0, t_decoder);
		
		in = 4'b0000;
	
		#10
		in = 4'b0001;
		#10
		in = 4'b0010;
		#10
		in = 4'b0011;
		#10
		in = 4'b0100;
		#10
		in = 4'b0101;	
		#10
		in = 4'b0110;
		#10
		in = 4'b0111;
		#10
		in = 4'b1000;
		#10
		in = 4'b1001;
		#10
		in = 4'b1010;	
		#10
		in = 4'b1011;
		#10
		in = 4'b1100;	
		#10
		in = 4'b1101;	
		#10
		in = 4'b1110;
		#10
		in = 4'b1111;
		#10;					
			
	end	
	
	// display meaning of input and output
	initial begin
		$display("\tinput: E3E2E1E0 output: D15D14D13D12D11D10D9D8D7D6D5D4D3D2D1D0");	
	end
	
	// print result
	initial begin
		$monitor("%t: input: %b output: %b", $time, in, out);	
	end
	
	
endmodule

PROGRAMS/verilog/COA/Assignment1/Assignment1COA-master/Q2/decoder/decoder.vcd
$date
	Mon Oct 16 15:03:01 2017
$end
$version
	Icarus Verilog
$end
$timescale
	100ps
$end
$scope module t_decoder $end
$var wire 16 ! out [0:15] $end
$var reg 4 " in [0:3] $end
$scope module inst $end
$var wire 4 # in [0:3] $end
$var reg 16 $ out [0:15] $end
$upscope $end
$upscope $end
$enddefinitions $end
#0
$dumpvars
b1 $
b0 #
b0 "
b1 !
$end
#100
b10 $
b10 !
b1 "
b1 #
#200
b100 $
b100 !
b10 "
b10 #
#300
b1000 $
b1000 !
b11 "
b11 #
#400
b10000 $
b10000 !
b100 "
b100 #
#500
b100000 $
b100000 !
b101 "
b101 #
#600
b1000000 $
b1000000 !
b110 "
b110 #
#700
b10000000 $
b10000000 !
b111 "
b111 #
#800
b100000000 $
b100000000 !
b1000 "
b1000 #
#900
b1000000000 $
b1000000000 !
b1001 "
b1001 #
#1000
b10000000000 $
b10000000000 !
b1010 "
b1010 #
#1100
b100000000000 $
b100000000000 !
b1011 "
b1011 #
#1200
b1000000000000 $
b1000000000000 !
b1100 "
b1100 #
#1300
b10000000000000 $
b10000000000000 !
b1101 "
b1101 #
#1400
b100000000000000 $
b100000000000000 !
b1110 "
b1110 #
#1500
b1000000000000000 $
b1000000000000000 !
b1111 "
b1111 #
