PROGRAMS/verilog/COA/Assignment1/chetanCOAass1/Assigment1/ans2/Encoder/prog2_enc.v
module encoder(
binary_out,
encoder_in,
enable
);

output [3:0] binary_out;
input enable;
input [15:0] encoder_in;

reg [3:0] binary_out;

always @(enable or encoder_in)
begin
	binary_out = 0;
	if(enable) begin
		case(encoder_in)
		16'h0002: binary_out = 1;
		16'h0004: binary_out = 2;
		16'h0008: binary_out = 3;
		16'h0010: binary_out = 4;
		16'h0020: binary_out = 5;
		16'h0040: binary_out = 6;
		16'h0080: binary_out = 7;
		16'h0100: binary_out = 8;
		16'h0200: binary_out = 9;
		16'h0400: binary_out = 10;
		16'h0800: binary_out = 11;
		16'h1000: binary_out = 12;
		16'h2000: binary_out = 13;
		16'h4000: binary_out = 14;
		16'h8000: binary_out = 15;
	endcase
	end
end

endmodule

PROGRAMS/verilog/COA/Assignment1/chetanCOAass1/Assigment1/ans2/Encoder/tb2_enc.v
`include "prog2_enc.v"

module tb2_enc;

reg [15:0] encoder_in;
reg enable;
wire [3:0] binary_out;

encoder A(binary_out,encoder_in,enable);

always begin
	enable = 1;
	encoder_in = 16'h0002;
	$monitor("Output = %b",binary_out);
	#1 encoder_in = 16'h0004;
	#2 encoder_in = 16'h0008;
	#3 encoder_in = 16'h0010;
	#4 encoder_in = 16'h0020;
	#5 encoder_in = 16'h0040;
	#6 encoder_in = 16'h0080;
	#7 encoder_in = 16'h0100;
	#8 encoder_in = 16'h0200;
	#9 encoder_in = 16'h0400;
	#10 encoder_in = 16'h0800;
	#11 encoder_in = 16'h1000;
	#12 encoder_in = 16'h2000;
	#13 encoder_in = 16'h4000;
	#14 encoder_in = 16'h8000;
	#15 encoder_in = 16'h0000;
	#16 $finish;
	end
endmodule

PROGRAMS/verilog/COA/Assignment1/chetanCOAass1/Assigment1/ans2/Decoder/prog2_enc.vcd
$date
	Mon Oct 15 16:08:49 2018
$end
$version
	Icarus Verilog
$end
$timescale
	1s
$end
$scope module tb2_enc $end
$var wire 4 ! binary_out [3:0] $end
$var reg 1 " enable $end
$var reg 16 # encoder_in [15:0] $end
$scope module A $end
$var wire 1 $ enable $end
$var wire 16 % encoder_in [15:0] $end
$var reg 4 & binary_out [3:0] $end
$upscope $end
$upscope $end
$enddefinitions $end
#0
$dumpvars
b1 &
b10 %
1$
b10 #
1"
b1 !
$end
#1
b10 &
b10 !
b100 #
b100 %
#3
b11 &
b11 !
b1000 #
b1000 %
#6
b100 &
b100 !
b10000 #
b10000 %
#10
b101 &
b101 !
b100000 #
b100000 %
#15
b110 &
b110 !
b1000000 #
b1000000 %
#21
b111 &
b111 !
b10000000 #
b10000000 %
#28
b1000 &
b1000 !
b100000000 #
b100000000 %
#36
b1001 &
b1001 !
b1000000000 #
b1000000000 %
#45
b1010 &
b1010 !
b10000000000 #
b10000000000 %
#55
b1011 &
b1011 !
b100000000000 #
b100000000000 %
#66
b1100 &
b1100 !
b1000000000000 #
b1000000000000 %
#78
b1101 &
b1101 !
b10000000000000 #
b10000000000000 %
#91
b1110 &
b1110 !
b100000000000000 #
b100000000000000 %
#105
b1111 &
b1111 !
b1000000000000000 #
b1000000000000000 %
#120
b0 &
b0 !
b0 #
b0 %
