PROGRAMS/verilog/COA/Assignment1/RaghavAss/COA Assignment/2_EncoderDecoder/decoder/decoder.v
module decoder(ip,op);
input [0:3]ip;
output [0:15]op;
	assign op[0]=(~ip[0]&~ip[1]&~ip[2]&~ip[3]),
	op[1]  =(~ip[0]&~ip[1]&~ip[2]&ip[3]),
	op[2]  =(~ip[0]&~ip[1]&ip[2]&~ip[3]),
	op[3]  =(~ip[0]&~ip[1]&ip[2]&ip[3]),
	op[4]  =(~ip[0]&ip[1]&~ip[2]&~ip[3]),
	op[5]  =(~ip[0]&ip[1]&~ip[2]&ip[3]),
	op[6]  =(~ip[0]&ip[1]&ip[2]&~ip[3]),
	op[7]  =(~ip[0]&ip[1]&ip[2]&ip[3]),
	op[8]  =(ip[0]&~ip[1]&~ip[2]&~ip[3]),
	op[9]  =(ip[0]&~ip[1]&~ip[2]&ip[3]),
	op[10] =(ip[0]&~ip[1]&ip[2]&~ip[3]),
	op[11] =(ip[0]&~ip[1]&ip[2]&ip[3]),
	op[12] =(ip[0]&ip[1]&~ip[2]&~ip[3]),
	op[13] =(ip[0]&ip[1]&~ip[2]&ip[3]),
	op[14] =(ip[0]&ip[1]&ip[2]&~ip[3]),
	op[15] =(ip[0]&ip[1]&ip[2]&ip[3]);
	
	
endmodule

PROGRAMS/verilog/COA/Assignment1/Assignment_1_Parth_Akshit/2_EncoderDecoder/decoder/decoder_tb.v
`include "decoder.v"
module decoder_tb;
reg [0:3]ip=4'b0000;
wire [0:15]op;
decoder dc(ip,op);
initial
	begin
		$dumpfile("decoder.vcd");
		$dumpvars(0,decoder_tb);
		$display("input    output\n");
		$monitor("%b     %b",ip,op);
		#5 ip=4'b 0001;
		#5 ip=4'b 0010;
		#5 ip=4'b 0011;
		#5 ip=4'b 0100;
		#5 ip=4'b 0101;
		#5 ip=4'b 0110;
		#5 ip=4'b 0111;
		#5 ip=4'b 1000;
		#5 ip=4'b 1001;
		#5 ip=4'b 1010;
		#5 ip=4'b 1011;
		#5 ip=4'b 1100;
		#5 ip=4'b 1101;
		#5 ip=4'b 1110;
		#5 ip=4'b 1111;
		#5
		$finish;
	end
endmodule

PROGRAMS/verilog/COA/Assignment1/2_EncoderDecoder/decoder/decoder.vcd
$date
	Mon Oct 15 22:26:16 2018
$end
$version
	Icarus Verilog
$end
$timescale
	1s
$end
$scope module decoder_tb $end
$var wire 16 ! op [0:15] $end
$var reg 4 " ip [0:3] $end
$scope module dc $end
$var wire 4 # ip [0:3] $end
$var wire 16 $ op [0:15] $end
$upscope $end
$upscope $end
$enddefinitions $end
#0
$dumpvars
b1000000000000000 $
b0 #
b0 "
b1000000000000000 !
$end
#5
b100000000000000 !
b100000000000000 $
b1 "
b1 #
#10
b10000000000000 !
b10000000000000 $
b10 "
b10 #
#15
b1000000000000 !
b1000000000000 $
b11 "
b11 #
#20
b100000000000 !
b100000000000 $
b100 "
b100 #
#25
b10000000000 !
b10000000000 $
b101 "
b101 #
#30
b1000000000 !
b1000000000 $
b110 "
b110 #
#35
b100000000 !
b100000000 $
b111 "
b111 #
#40
b10000000 !
b10000000 $
b1000 "
b1000 #
#45
b1000000 !
b1000000 $
b1001 "
b1001 #
#50
b100000 !
b100000 $
b1010 "
b1010 #
#55
b10000 !
b10000 $
b1011 "
b1011 #
#60
b1000 !
b1000 $
b1100 "
b1100 #
#65
b100 !
b100 $
b1101 "
b1101 #
#70
b10 !
b10 $
b1110 "
b1110 #
#75
b1 !
b1 $
b1111 "
b1111 #
