PROGRAMS/verilog/COA/Assignment1/Assignment1COA-master/Q6/6a/network.v
//Module for machine a
module amodule(input binput,output reg boutput);
	//Whenever b sends an input, the output boutput is generated which is later printed in the testbench along with the timestamp	
	always@(binput) begin
		boutput=binput;	
	end
endmodule
//Module for machine b
module bmodule(input ainput,output reg aoutput);
	//Whenever a sends an input, the output aoutput is generated which is later printed in the testbench along with the timestamp
	always@(ainput) begin
		aoutput=ainput;	
	end
endmodule

PROGRAMS/verilog/COA/Assignment1/Assignment1COA-master/Q6/6a/t_network.v
`timescale 1ns/100ps
module testbench;
	// inputs
	reg ainput;
	reg binput;
	//outputs
	wire aoutput;
	wire boutput;

	integer i;
	// amodule is the machine a, where binput is the input given by b and boutput is the corresponding output generated
	amodule inst1 (binput,boutput);
	// bmodule is the machine b, where ainput is the input given by a and aoutput is the corresponding output generated
	bmodule inst2 (ainput,aoutput);
	
	initial begin 
		$dumpfile("network.vcd");
		$dumpvars(0, testbench);
		ainput=1'b1;
		binput=1'b0;
		for(i=1;i<=5;i=i+1) begin
			// ainput is varied with time
			#10 ainput=~ainput;
			// displaying the output
				#0 $display("Time=%3d Ainput=%d Aoutput=%d",$time,ainput,aoutput);
			// binput is varied with time			
			#20 binput=~binput;	
			// displaying the output
				#0 $display("Time=%3d Binput=%d Boutput=%d",$time,binput,boutput);	
				
		end	
	end
endmodule

PROGRAMS/verilog/COA/Assignment1/Assignment1COA-master/Q6/6a/network.vcd
$date
	Mon Oct 16 22:37:58 2017
$end
$version
	Icarus Verilog
$end
$timescale
	100ps
$end
$scope module testbench $end
$var wire 1 ! aoutput $end
$var wire 1 " boutput $end
$var reg 1 # ainput $end
$var reg 1 $ binput $end
$var integer 32 % i [31:0] $end
$scope module inst1 $end
$var wire 1 & binput $end
$var reg 1 ' boutput $end
$upscope $end
$scope module inst2 $end
$var wire 1 ( ainput $end
$var reg 1 ) aoutput $end
$upscope $end
$upscope $end
$enddefinitions $end
#0
$dumpvars
1)
1(
0'
0&
b1 %
0$
1#
0"
1!
$end
#100
0)
0!
0#
0(
#300
b10 %
1'
1"
1$
1&
#400
1)
1!
1#
1(
#600
b11 %
0'
0"
0$
0&
#700
0)
0!
0#
0(
#900
b100 %
1'
1"
1$
1&
#1000
1)
1!
1#
1(
#1200
b101 %
0'
0"
0$
0&
#1300
0)
0!
0#
0(
#1500
b110 %
1'
1"
1$
1&
