PROGRAMS/verilog/COA/Assignment1/Assignment1COA-master/Q6/6b/networkb.v
//Module for machine b
module bmodule(input binput,output reg [3:0] boutput);
	// binput is the input given and boutput is the output generated	
	always@(binput) begin
		// 4 bit output generated by b(1 1 1 1), IT CAN BE CHANGED BY THE USER		
		boutput=15;
	end	
endmodule
//Module for machine a
module amodule(input[3:0] ainput,output reg [3:0] aoutput);
	// ainput is the input given and aoutput is the output generated
	always@(ainput) begin
		aoutput=ainput;	
	end	
endmodule

PROGRAMS/verilog/COA/Assignment1/Assignment1COA-master/Q6/6b/t_networkb.v
`timescale 1ns/100ps
module testbench;
	//inputs
	reg binput;
	reg[3:0] ainput;
	//random number generated	
	reg[15:0] randomnumber;
	//outputs
	wire[3:0] aoutput;
	wire[3:0] boutput;

	integer i,j;	
	// machine b along with inputs and outputs
	bmodule inst1 	(binput,boutput);
	// machine a along with inputs and outputs
	amodule inst2	(ainput,aoutput);

	initial begin 
		$dumpfile("networkb.vcd");
		$dumpvars(0, testbench);
		binput=1'b0;
				
		for(i=1;i<=5;i=i+1) begin
			#10		
			//generating random number			
			randomnumber=$urandom & 15;	
			#randomnumber
			// input is sent to b
			binput=~binput;
			// output of b is given to a as input
			ainput=boutput;
			// output from a is generated as aoutput
			#0 
			// printing the output of a (aoutput) and the input to b (binput) 
			$display("Message sent by A:%b, 4 bit message from B:%b %b %b %b ,time(random)=%3d\n"
			,binput,aoutput[3],aoutput[2],aoutput[1],aoutput[0],$time);
		end 
	end
endmodule

PROGRAMS/verilog/COA/Assignment1/Assignment1COA-master/Q6/6b/networkb.vcd
$date
	Mon Oct 16 23:06:09 2017
$end
$version
	Icarus Verilog
$end
$timescale
	100ps
$end
$scope module testbench $end
$var wire 4 ! aoutput [3:0] $end
$var wire 4 " boutput [3:0] $end
$var reg 4 # ainput [3:0] $end
$var reg 1 $ binput $end
$var integer 32 % i [31:0] $end
$var reg 16 & randomnumber [15:0] $end
$scope module inst1 $end
$var wire 1 ' binput $end
$var reg 4 ( boutput [3:0] $end
$upscope $end
$scope module inst2 $end
$var wire 4 ) ainput [3:0] $end
$var reg 4 * aoutput [3:0] $end
$upscope $end
$upscope $end
$enddefinitions $end
#0
$dumpvars
bx *
bx )
b1111 (
0'
bx &
b1 %
0$
bx #
b1111 "
bx !
$end
#100
b100 &
#140
b10 %
b1111 *
b1111 !
b1111 #
b1111 )
1$
1'
#240
b1 &
#250
b11 %
0$
0'
#350
b1001 &
#440
b100 %
1$
1'
#540
b11 &
#570
b101 %
0$
0'
#670
b1101 &
#800
b110 %
1$
1'
