PROGRAMS/verilog/COA/Assignment1/chetanCOAass1/Assigment1/ans3/prog3.v
module half_add(
a	,//first input
b	,//second input
sum	,//sum output
co	//carry output
);

// input declaration
input a;
input b;

//output declaration
output sum;
output co;

//port data types
wire a;
wire b;
wire sum;
wire co;

//code starts
assign {co,sum} = a+b;

endmodule //End of module

PROGRAMS/verilog/COA/Assignment1/chetanCOAass1/Assigment1/ans4/prog4.v
`include "prog3.v"

module full_add(a,b,c,ca,sum1);
input a;
input b;
input c;
inout sumo;
inout co;
output sum1;
inout c1;
output ca;

half_add A(a,b,sumo,co);

half_add B(sumo,c,sum1,c1);

or C(ca,c1,co);

endmodule

PROGRAMS/verilog/COA/Assignment1/chetanCOAass1/Assigment1/ans4/tb4.v
`include "prog4.v"

module tb4;

reg a=0;
reg b=0;
reg c=0;
wire ca;
wire sum1;

full_add A(a,b,c,ca,sum1);

always begin
	
	a=0;
	b=0;
	c=0;
	$monitor("A=%b B=%b Ci=%b S=%b C=%b",a,b,c,sum1,ca);	
	#1 a=1;
	#2 a=0;b=1;
	#3 a=1;b=1;
	#4 a=0;b=0;c=1;
	#5 a=1;b=0;c=1;
	#6 a=0;b=1;c=1;
	#7 a=1;b=1;c=1;
	#8 $finish;	
	end
endmodule

PROGRAMS/verilog/COA/Assignment1/chetanCOAass1/Assigment1/ans4/prog4.vcd
$date
	Mon Oct 15 16:13:05 2018
$end
$version
	Icarus Verilog
$end
$timescale
	1s
$end
$scope module tb4 $end
$var wire 1 ! ca $end
$var wire 1 " sum1 $end
$var reg 1 # a $end
$var reg 1 $ b $end
$var reg 1 % c $end
$scope module A $end
$var wire 1 & a $end
$var wire 1 ' b $end
$var wire 1 ( c $end
$var wire 1 ) c1 $end
$var wire 1 ! ca $end
$var wire 1 * co $end
$var wire 1 " sum1 $end
$var wire 1 + sumo $end
$scope module A $end
$var wire 1 & a $end
$var wire 1 ' b $end
$var wire 1 * co $end
$var wire 1 + sum $end
$upscope $end
$scope module B $end
$var wire 1 + a $end
$var wire 1 ( b $end
$var wire 1 ) co $end
$var wire 1 " sum $end
$upscope $end
$upscope $end
$upscope $end
$enddefinitions $end
#0
$dumpvars
0+
0*
0)
0(
0'
0&
0%
0$
0#
0"
0!
$end
#1
1"
1+
1#
1&
#3
1$
1'
0#
0&
#6
0"
1!
0+
1*
1#
1&
#10
0!
1"
0*
1%
1(
0$
0'
0#
0&
#15
1!
0"
1)
1+
1#
1&
#21
1$
1'
0#
0&
#28
1"
0)
0+
1*
1#
1&
