PROGRAMS/verilog/COA/Assignment1/Assignment1COA-master/Q4/fullAdder.v
module halfAdder (output reg sum, output reg carry, input op1, input op2);

	// thread for half adder operations
	always @ (op1 or op2) begin
	
		// sum bit of two operands
		sum = op1 ^ op2;
		// carry bit of two operands
		carry = op1 & op2;
		
	end

endmodule

module fullAdder (output sum, output carry, input op1, input op2,input op3);
	
	wire isum,i1carry,i2carry;
	// thread for full adder operations
	//'i' stands for intermediate
		
		// using half adder the first time
		halfAdder inst1 (isum,i1carry,op1,op2);
		// calculating the sum
		halfAdder inst2 (sum,i2carry,isum,op3);
		// calculating the carry
		assign carry = i1carry|i2carry;
		

endmodule

PROGRAMS/verilog/COA/Assignment1/Assignment1COA-master/Q4/t_fullAdder.v
`timescale 1ns/100ps

module t_fullAdder;

	// outputs 
	wire sum;
	wire carry;
	// inputs 
	reg op2;
	reg op1;
	reg op3;
	// full Adder thread instantiated
	fullAdder inst (sum, carry, op1, op2, op3);
	
	// check for various input combinations
	initial begin
	
		$dumpfile("fullAdder.vcd");
		$dumpvars(0, t_fullAdder);
		
		op1 = 1'b0;
		op2 = 1'b0;
		op3 = 1'b0;
	
		#10
		op1 = 1'b0;
		op2 = 1'b0;
		op3 = 1'b1;	
		
		#10
		op1 = 1'b0;
		op2 = 1'b1;
		op3 = 1'b0;
		
		#10
		op1 = 1'b0;
		op2 = 1'b1;
		op3 = 1'b1;
		
		#10
		op1 = 1'b1;
		op2 = 1'b0;
		op3 = 1'b0;
	
		#10
		op1 = 1'b1;
		op2 = 1'b0;
		op3 = 1'b1;	
		
		#10
		op1 = 1'b1;
		op2 = 1'b1;
		op3 = 1'b0;
		
		#10
		op1 = 1'b1;
		op2 = 1'b1;
		op3 = 1'b1;
		
		#10;
			
	end	
	
	
	// print result
	initial begin
		$monitor("%t: operand1: %b operand2: %b operand3: %b \n\t\t\t carry: %b sum: %b\n", $time, op1, op2, op3, carry, sum);	
	end
	
	
endmodule

PROGRAMS/verilog/COA/Assignment1/Assignment1COA-master/Q4/fullAdder.vcd
$date
	Mon Oct 16 21:22:15 2017
$end
$version
	Icarus Verilog
$end
$timescale
	100ps
$end
$scope module t_fullAdder $end
$var wire 1 ! carry $end
$var wire 1 " sum $end
$var reg 1 # op1 $end
$var reg 1 $ op2 $end
$var reg 1 % op3 $end
$scope module inst $end
$var wire 1 ! carry $end
$var wire 1 & i1carry $end
$var wire 1 ' i2carry $end
$var wire 1 ( isum $end
$var wire 1 ) op1 $end
$var wire 1 * op2 $end
$var wire 1 + op3 $end
$var wire 1 " sum $end
$scope module inst1 $end
$var wire 1 ) op1 $end
$var wire 1 * op2 $end
$var reg 1 , carry $end
$var reg 1 - sum $end
$upscope $end
$scope module inst2 $end
$var wire 1 ( op1 $end
$var wire 1 + op2 $end
$var reg 1 . carry $end
$var reg 1 / sum $end
$upscope $end
$upscope $end
$upscope $end
$enddefinitions $end
#0
$dumpvars
0/
0.
0-
0,
0+
0*
0)
0(
0'
0&
0%
0$
0#
0"
0!
$end
#100
1/
1"
1%
1+
#200
1-
1(
0%
0+
1$
1*
#300
1!
1.
1'
0/
0"
1%
1+
#400
0!
0.
0'
1/
1"
0%
0+
0$
0*
1#
1)
#500
1!
1.
1'
0/
0"
1%
1+
#600
0.
0'
1,
1&
0-
0(
0%
0+
1$
1*
#700
1/
1"
1%
1+
