PROGRAMS/verilog/COA/Assignment2/5_RegFile/reg_file.v
module reg_file(regRNum1,regRNum2,wReg,Data,RegWrite,reset,clk,rData1,rData2);

	input [4:0]regRNum1,regRNum2,wReg;				
	input [63:0]Data;									
	input RegWrite,reset,clk;							
	output [63:0]rData1,rData2;							
	integer k;
	reg [63:0] regFile[0:31];							




	assign rData1=regFile[regRNum1];
	assign rData2=regFile[regRNum2];

	always@(posedge clk)
	begin	
		if(reset)
		begin
			for(k=0;k<32;k=k+1)
			begin
				regFile[k] <= 64'b0;					
			end
		end
		else
		begin
			if(RegWrite)
			begin
				regFile[wReg] <= Data;
			end
		end
	end

endmodule

PROGRAMS/verilog/COA/Assignment2/5_RegFile/reg_file_tb.v
`include "reg_file.v"
module reg_file_tb;
reg [4:0]regRNum1,regRNum2,wReg;
reg [63:0]data;
reg RegWrite,clk,reset;
wire [63:0]rData1,rData2;
integer k;

reg_file A(regRNum1,regRNum2,wReg,data,RegWrite,reset,clk,rData1,rData2);

initial 
begin
	clk=1'b0;
	repeat(120)
		#5 clk = ~clk;
end

initial
begin
	$dumpfile("reg_file.vcd");
	$dumpvars(0,reg_file_tb);
	#1 reset = 1'b1; RegWrite=1'b0;
	#5 reset = 1'b0;
end

initial
begin
	#7
	for(k=0;k<32;k=k+1)
	begin
		wReg=k;
		data=k*10;
		RegWrite=1;
		#10 RegWrite=0;
	end
end

initial
begin
	#350
	for(k=0;k<32;k=k+2)
	begin
		regRNum1=k;
		regRNum2=k+1;
		#5;
		$display("reg[%2d]=%3d, reg[%2d]=%3d",regRNum1,rData1,regRNum2,rData2);
	end
end

initial 
begin	
	#450 $finish;
end

endmodule

PROGRAMS/verilog/COA/Assignment2/5_RegFile/reg_file.vcd
$date
	Thu Oct 25 17:50:58 2018
$end
$version
	Icarus Verilog
$end
$timescale
	1s
$end
$scope module reg_file_tb $end
$var wire 64 ! rData1 [63:0] $end
$var wire 64 " rData2 [63:0] $end
$var reg 1 # RegWrite $end
$var reg 1 $ clk $end
$var reg 64 % data [63:0] $end
$var integer 32 & k [31:0] $end
$var reg 5 ' regRNum1 [4:0] $end
$var reg 5 ( regRNum2 [4:0] $end
$var reg 1 ) reset $end
$var reg 5 * wReg [4:0] $end
$scope module A $end
$var wire 64 + Data [63:0] $end
$var wire 1 , RegWrite $end
$var wire 1 - clk $end
$var wire 64 . rData1 [63:0] $end
$var wire 64 / rData2 [63:0] $end
$var wire 5 0 regRNum1 [4:0] $end
$var wire 5 1 regRNum2 [4:0] $end
$var wire 1 2 reset $end
$var wire 5 3 wReg [4:0] $end
$var integer 32 4 k [31:0] $end
$upscope $end
$upscope $end
$enddefinitions $end
#0
$dumpvars
bx 4
bx 3
x2
bx 1
bx 0
bx /
bx .
0-
x,
bx +
bx *
x)
bx (
bx '
bx &
bx %
0$
x#
bx "
bx !
$end
#1
0#
0,
1)
12
#5
b100000 4
1$
1-
#6
0)
02
#7
1#
1,
b0 %
b0 +
b0 *
b0 3
b0 &
#10
0$
0-
#15
1$
1-
#17
b1010 %
b1010 +
b1 *
b1 3
b1 &
1#
1,
#20
0$
0-
#25
1$
1-
#27
b10100 %
b10100 +
b10 *
b10 3
b10 &
1#
1,
#30
0$
0-
#35
1$
1-
#37
b11110 %
b11110 +
b11 *
b11 3
b11 &
1#
1,
#40
0$
0-
#45
1$
1-
#47
b101000 %
b101000 +
b100 *
b100 3
b100 &
1#
1,
#50
0$
0-
#55
1$
1-
#57
b110010 %
b110010 +
b101 *
b101 3
b101 &
1#
1,
#60
0$
0-
#65
1$
1-
#67
b111100 %
b111100 +
b110 *
b110 3
b110 &
1#
1,
#70
0$
0-
#75
1$
1-
#77
b1000110 %
b1000110 +
b111 *
b111 3
b111 &
1#
1,
#80
0$
0-
#85
1$
1-
#87
b1010000 %
b1010000 +
b1000 *
b1000 3
b1000 &
1#
1,
#90
0$
0-
#95
1$
1-
#97
b1011010 %
b1011010 +
b1001 *
b1001 3
b1001 &
1#
1,
#100
0$
0-
#105
1$
1-
#107
b1100100 %
b1100100 +
b1010 *
b1010 3
b1010 &
1#
1,
#110
0$
0-
#115
1$
1-
#117
b1101110 %
b1101110 +
b1011 *
b1011 3
b1011 &
1#
1,
#120
0$
0-
#125
1$
1-
#127
b1111000 %
b1111000 +
b1100 *
b1100 3
b1100 &
1#
1,
#130
0$
0-
#135
1$
1-
#137
b10000010 %
b10000010 +
b1101 *
b1101 3
b1101 &
1#
1,
#140
0$
0-
#145
1$
1-
#147
b10001100 %
b10001100 +
b1110 *
b1110 3
b1110 &
1#
1,
#150
0$
0-
#155
1$
1-
#157
b10010110 %
b10010110 +
b1111 *
b1111 3
b1111 &
1#
1,
#160
0$
0-
#165
1$
1-
#167
b10100000 %
b10100000 +
b10000 *
b10000 3
b10000 &
1#
1,
#170
0$
0-
#175
1$
1-
#177
b10101010 %
b10101010 +
b10001 *
b10001 3
b10001 &
1#
1,
#180
0$
0-
#185
1$
1-
#187
b10110100 %
b10110100 +
b10010 *
b10010 3
b10010 &
1#
1,
#190
0$
0-
#195
1$
1-
#197
b10111110 %
b10111110 +
b10011 *
b10011 3
b10011 &
1#
1,
#200
0$
0-
#205
1$
1-
#207
b11001000 %
b11001000 +
b10100 *
b10100 3
b10100 &
1#
1,
#210
0$
0-
#215
1$
1-
#217
b11010010 %
b11010010 +
b10101 *
b10101 3
b10101 &
1#
1,
#220
0$
0-
#225
1$
1-
#227
b11011100 %
b11011100 +
b10110 *
b10110 3
b10110 &
1#
1,
#230
0$
0-
#235
1$
1-
#237
b11100110 %
b11100110 +
b10111 *
b10111 3
b10111 &
1#
1,
#240
0$
0-
#245
1$
1-
#247
b11110000 %
b11110000 +
b11000 *
b11000 3
b11000 &
1#
1,
#250
0$
0-
#255
1$
1-
#257
b11111010 %
b11111010 +
b11001 *
b11001 3
b11001 &
1#
1,
#260
0$
0-
#265
1$
1-
#267
b100000100 %
b100000100 +
b11010 *
b11010 3
b11010 &
1#
1,
#270
0$
0-
#275
1$
1-
#277
b100001110 %
b100001110 +
b11011 *
b11011 3
b11011 &
1#
1,
#280
0$
0-
#285
1$
1-
#287
b100011000 %
b100011000 +
b11100 *
b11100 3
b11100 &
1#
1,
#290
0$
0-
#295
1$
1-
#297
b100100010 %
b100100010 +
b11101 *
b11101 3
b11101 &
1#
1,
#300
0$
0-
#305
1$
1-
#307
b100101100 %
b100101100 +
b11110 *
b11110 3
b11110 &
1#
1,
#310
0$
0-
#315
1$
1-
#317
b100110110 %
b100110110 +
b11111 *
b11111 3
b11111 &
1#
1,
#320
0$
0-
#325
1$
1-
#327
b100000 &
0#
0,
#330
0$
0-
#335
1$
1-
#340
0$
0-
#345
1$
1-
#350
0$
0-
b1 (
b1 1
b1010 "
b1010 /
b0 '
b0 0
b0 !
b0 .
b0 &
#355
1$
1-
b11 (
b11 1
b11110 "
b11110 /
b10 '
b10 0
b10100 !
b10100 .
b10 &
#360
0$
0-
b101 (
b101 1
b110010 "
b110010 /
b100 '
b100 0
b101000 !
b101000 .
b100 &
#365
1$
1-
b111 (
b111 1
b1000110 "
b1000110 /
b110 '
b110 0
b111100 !
b111100 .
b110 &
#370
0$
0-
b1001 (
b1001 1
b1011010 "
b1011010 /
b1000 '
b1000 0
b1010000 !
b1010000 .
b1000 &
#375
1$
1-
b1011 (
b1011 1
b1101110 "
b1101110 /
b1010 '
b1010 0
b1100100 !
b1100100 .
b1010 &
#380
0$
0-
b1101 (
b1101 1
b10000010 "
b10000010 /
b1100 '
b1100 0
b1111000 !
b1111000 .
b1100 &
#385
1$
1-
b1111 (
b1111 1
b10010110 "
b10010110 /
b1110 '
b1110 0
b10001100 !
b10001100 .
b1110 &
#390
0$
0-
b10001 (
b10001 1
b10101010 "
b10101010 /
b10000 '
b10000 0
b10100000 !
b10100000 .
b10000 &
#395
1$
1-
b10011 (
b10011 1
b10111110 "
b10111110 /
b10010 '
b10010 0
b10110100 !
b10110100 .
b10010 &
#400
0$
0-
b10101 (
b10101 1
b11010010 "
b11010010 /
b10100 '
b10100 0
b11001000 !
b11001000 .
b10100 &
#405
1$
1-
b10111 (
b10111 1
b11100110 "
b11100110 /
b10110 '
b10110 0
b11011100 !
b11011100 .
b10110 &
#410
0$
0-
b11001 (
b11001 1
b11111010 "
b11111010 /
b11000 '
b11000 0
b11110000 !
b11110000 .
b11000 &
#415
1$
1-
b11011 (
b11011 1
b100001110 "
b100001110 /
b11010 '
b11010 0
b100000100 !
b100000100 .
b11010 &
#420
0$
0-
b11101 (
b11101 1
b100100010 "
b100100010 /
b11100 '
b11100 0
b100011000 !
b100011000 .
b11100 &
#425
1$
1-
b11111 (
b11111 1
b100110110 "
b100110110 /
b11110 '
b11110 0
b100101100 !
b100101100 .
b11110 &
#430
0$
0-
b100000 &
