PROGRAMS/verilog/COA/Assignment1/Assignment1COA-master/Q7/Dff.v
/**
*	Module for D flip-flop
*	By: Omkar Prabhu 16CO233
*	15th October 2017
*/

/**
* Module for D master slave flip-flop
*/
module Dff (output q, output  qn, input d, input clk, input res);

	reg nclk;
	wire qi, qni;
	
	// active low reset signal
	wire new_d;
	assign new_d = d & res;
	
	// D latch 1
	Dl inst1 (qi, qni, new_d, nclk);
	// D latch 2
	Dl inst2 (q, qn, qi, clk);
	
	// complement of clock
	always @ (clk) begin
		nclk <= ~clk;
	end
		
endmodule


/**
* Module for RS Latch using nor gates
*/
module RSl (output reg q, output reg qn, input r, input s);

	// rs latch modeling
	always @(q, qn, r, s) begin
		q <= ~ (qn | r);
		qn <= ~ (q | s);
		
	end

endmodule



/**
* Module for D Latch using RS latch
*/
module Dl (output q, output qn, input d, input clk);
	
	reg r, s;
	
	// using rs latch module
	RSl RSlinstDl (q, qn, r, s);
	
	// d latch modelling
	always @ (r, s, d, clk) begin
		r <= (~ d) & clk;
		s <= d & clk;
	end
	

endmodule

PROGRAMS/verilog/COA/Assignment1/Assignment1COA-master/Q7/t_Dff.v
/**
*	Test bench for D flip-flop
*	By: Omkar Prabhu 16CO233
*	15th October 2017
*/

`timescale 1ns/100ps

module t_Dff;

	// outputs 
	wire q;
	wire qn;
	// inputs 
	reg d;
	reg clk;
	// active low reset input 
	reg res;
	// D flip-flop thread instantiated
	Dff inst (q, qn, d, clk, res);
	
	// check for various input combinations
	initial begin
	
		$dumpfile("Dff.vcd");
		$dumpvars(0, t_Dff);
		
		d = 1'b0;
		clk = 1'b0;
		res = 1'b1;
			
		#6
			d = 1'b1;			
		#6
			d = 1'b0;
		#6
			d = 1'b0;
		#6; 
			d = 1'b1;
		#6;
			res = 1'b0;
			d = 1'b1;
		#6;
			d = 1'b0;
		#6;
		
		#6
			d = 1'b1;			
		#6
			d = 1'b0;
		#6
			d = 1'b0;
		#6;
			res = 1'b1;
			d = 1'b0;
		#6;
			d = 1'b1;
		#6;
			d = 1'b0;
		#6;
		#6
			d = 1'b1;			
		#6
			d = 1'b1;
		#6
			d = 1'b1;
		#6;
			d = 1'b0;
		#6;
			d = 1'b1;
		#6;
		#6;
			d = 1'b0;
		#6;
		#6;
			d = 1'b1;			
		#6
			d = 1'b0;
		#6
			d = 1'b1;
		#6;
			d = 1'b1;
		#6;
			d = 1'b1;
		#6;
			d = 1'b0;
		#6;
			
	end	
	
	initial begin
		repeat (30) begin
			#5 clk = ~ clk;
		end
	end
	
	// print result
	initial begin
		$monitor("%t: d: %b clk: %b reset : %b \t\t\t q: %b q': %b\n", $time, d, clk, res, q, qn);	
	end
	
	
endmodule

PROGRAMS/verilog/COA/Assignment1/Assignment1COA-master/Q7/Dff.vcd
$date
	Mon Oct 16 17:41:59 2017
$end
$version
	Icarus Verilog
$end
$timescale
	100ps
$end
$scope module t_Dff $end
$var wire 1 ! q $end
$var wire 1 " qn $end
$var reg 1 # clk $end
$var reg 1 $ d $end
$var reg 1 % res $end
$scope module inst $end
$var wire 1 & clk $end
$var wire 1 ' d $end
$var wire 1 ( new_d $end
$var wire 1 ! q $end
$var wire 1 ) qi $end
$var wire 1 " qn $end
$var wire 1 * qni $end
$var wire 1 + res $end
$var reg 1 , nclk $end
$scope module inst1 $end
$var wire 1 - clk $end
$var wire 1 ( d $end
$var wire 1 ) q $end
$var wire 1 * qn $end
$var reg 1 . r $end
$var reg 1 / s $end
$scope module RSlinstDl $end
$var wire 1 0 r $end
$var wire 1 1 s $end
$var reg 1 2 q $end
$var reg 1 3 qn $end
$upscope $end
$upscope $end
$scope module inst2 $end
$var wire 1 & clk $end
$var wire 1 ) d $end
$var wire 1 ! q $end
$var wire 1 " qn $end
$var reg 1 4 r $end
$var reg 1 5 s $end
$scope module RSlinstDl $end
$var wire 1 6 r $end
$var wire 1 7 s $end
$var reg 1 8 q $end
$var reg 1 9 qn $end
$upscope $end
$upscope $end
$upscope $end
$upscope $end
$enddefinitions $end
#0
$dumpvars
x9
x8
07
06
05
04
13
02
01
10
0/
1.
1-
1,
1+
1*
0)
0(
0'
0&
1%
0$
0#
x"
x!
$end
#50
19
1"
08
0!
0.
00
14
16
0,
0-
1#
1&
#60
1(
1$
1'
#100
12
1)
03
0*
1/
11
04
06
1,
1-
0#
0&
#120
13
1*
02
0)
0/
01
1.
10
0(
0$
0'
#150
0.
00
14
16
0,
0-
1#
1&
#200
1.
10
04
06
1,
1-
0#
0&
#240
12
1)
03
0*
1/
11
0.
00
1(
1$
1'
#250
18
1!
09
0"
0/
01
15
17
0,
0-
1#
1&
#300
13
1*
02
0)
1.
10
05
07
1,
1-
0(
0#
0&
0%
0+
#350
19
1"
08
0!
0.
00
14
16
0,
0-
1#
1&
#360
0$
0'
#400
1.
10
04
06
1,
1-
0#
0&
#450
0.
00
14
16
0,
0-
1#
1&
#480
1$
1'
#500
1.
10
04
06
1,
1-
0#
0&
#540
0$
0'
#550
0.
00
14
16
0,
0-
1#
1&
#600
1.
10
04
06
1,
1-
0#
0&
#650
0.
00
14
16
0,
0-
1#
1&
#660
1%
1+
#700
1.
10
04
06
1,
1-
0#
0&
#720
12
1)
03
0*
1/
11
0.
00
1(
1$
1'
#750
18
1!
09
0"
0/
01
15
17
0,
0-
1#
1&
#780
0(
0$
0'
#800
13
1*
02
0)
1.
10
05
07
1,
1-
0#
0&
#850
19
1"
08
0!
0.
00
14
16
0,
0-
1#
1&
#900
12
1)
03
0*
1/
11
04
06
1,
1-
1(
0#
0&
1$
1'
#950
18
1!
09
0"
0/
01
15
17
0,
0-
1#
1&
#1000
1/
11
05
07
1,
1-
0#
0&
#1050
0/
01
15
17
0,
0-
1#
1&
#1080
0(
0$
0'
#1100
13
1*
02
0)
1.
10
05
07
1,
1-
0#
0&
#1140
12
1)
03
0*
1/
11
0.
00
1(
1$
1'
#1150
0/
01
15
17
0,
0-
1#
1&
#1200
1/
11
05
07
1,
1-
0#
0&
#1250
0/
01
15
17
0,
0-
1#
1&
#1260
0(
0$
0'
#1300
13
1*
02
0)
1.
10
05
07
1,
1-
0#
0&
#1350
19
1"
08
0!
0.
00
14
16
0,
0-
1#
1&
#1380
1(
1$
1'
#1400
12
1)
03
0*
1/
11
04
06
1,
1-
0#
0&
#1440
13
1*
02
0)
0/
01
1.
10
0(
0$
0'
#1450
0.
00
14
16
0,
0-
1#
1&
#1500
12
1)
03
0*
1/
11
04
06
1,
1-
1(
0#
0&
1$
1'
#1680
13
1*
02
0)
0/
01
1.
10
0(
0$
0'
