PROGRAMS/verilog/COA/Assignment1/Assignment_1_Parth_Akshit/2_EncoderDecoder/encoder/encoder.v
module encoder(ip,op);
input [0:15]ip;
output [0:3]op;
		assign op[0]=(ip[8]|ip[9]|ip[10]|ip[11]|ip[12]|ip[13]|ip[14]|ip[15]),
		op[1]=(ip[4]|ip[5]|ip[6]|ip[7]|ip[12]|ip[13]|ip[14]|ip[15]),
		op[2]=(ip[2]|ip[3]|ip[6]|ip[7]|ip[11]|ip[10]|ip[14]|ip[15]),
		op[3]=(ip[1]|ip[3]|ip[5]|ip[7]|ip[9]|ip[11]|ip[13]|ip[15]);
endmodule

PROGRAMS/verilog/COA/Assignment1/RaghavAss/COA Assignment/2_EncoderDecoder/encoder/encoder_tb.v
`include "encoder.v"
module encoder_tb;
wire [0:3]op;
reg [0:15]ip=1000000000000000;
encoder ec(ip,op);
initial
	begin
		$dumpfile("encoder.vcd");
		$dumpvars(0,encoder_tb);
		$display("input              output\n");
		$monitor("%b    %b",ip,op);
		#5 ip=16'b 0100000000000000;
		#5 ip=16'b 0010000000000000;
		#5 ip=16'b 0001000000000000;
		#5 ip=16'b 0000100000000000;
		#5 ip=16'b 0000010000000000;
		#5 ip=16'b 0000001000000000;
		#5 ip=16'b 0000000100000000;
		#5 ip=16'b 0000000010000000;
		#5 ip=16'b 0000000001000000;
		#5 ip=16'b 0000000000100000;
		#5 ip=16'b 0000000000010000;
		#5 ip=16'b 0000000000001000;
		#5 ip=16'b 0000000000000100;
		#5 ip=16'b 0000000000000010;
		#5 ip=16'b 0000000000000001;
		$finish;
	end
endmodule

PROGRAMS/verilog/COA/Assignment1/Assignment_1_Parth_Akshit/2_EncoderDecoder/encoder/encoder.vcd
$date
	Mon Oct 15 22:28:10 2018
$end
$version
	Icarus Verilog
$end
$timescale
	1s
$end
$scope module encoder_tb $end
$var wire 4 ! op [0:3] $end
$var reg 16 " ip [0:15] $end
$scope module ec $end
$var wire 16 # ip [0:15] $end
$var wire 4 $ op [0:3] $end
$upscope $end
$upscope $end
$enddefinitions $end
#0
$dumpvars
b0 $
b1000000000000000 #
b1000000000000000 "
b0 !
$end
#5
b1 !
b1 $
b100000000000000 "
b100000000000000 #
#10
b10 !
b10 $
b10000000000000 "
b10000000000000 #
#15
b11 !
b11 $
b1000000000000 "
b1000000000000 #
#20
b100 !
b100 $
b100000000000 "
b100000000000 #
#25
b101 !
b101 $
b10000000000 "
b10000000000 #
#30
b110 !
b110 $
b1000000000 "
b1000000000 #
#35
b111 !
b111 $
b100000000 "
b100000000 #
#40
b1000 !
b1000 $
b10000000 "
b10000000 #
#45
b1001 !
b1001 $
b1000000 "
b1000000 #
#50
b1010 !
b1010 $
b100000 "
b100000 #
#55
b1011 !
b1011 $
b10000 "
b10000 #
#60
b1100 !
b1100 $
b1000 "
b1000 #
#65
b1101 !
b1101 $
b100 "
b100 #
#70
b1110 !
b1110 $
b10 "
b10 #
#75
b1111 !
b1111 $
b1 "
b1 #
