PROGRAMS/verilog/COA/Assignment1/Assignment1COA-master/Q2/encoder/encoder.v
/**
*	Module for 16:4 encoder
*	By: Omkar Prabhu 16CO233
*	13th October 2017
*/

module encoder (output reg [0:3] out, input [0:15] in);

	// thread to decode input
	always @ (in) begin
		// check which input and give corresponding output		
		case (in) 
			16'b0000000000000001 : out = 4'b0000; 
			16'b0000000000000010 : out = 4'b0001; 
			16'b0000000000000100 : out = 4'b0010; 
			16'b0000000000001000 : out = 4'b0011; 
			16'b0000000000010000 : out = 4'b0100; 
			16'b0000000000100000 : out = 4'b0101; 
			16'b0000000001000000 : out = 4'b0110; 
			16'b0000000010000000 : out = 4'b0111; 
			16'b0000000100000000 : out = 4'b1000; 
			16'b0000001000000000 : out = 4'b1001; 
			16'b0000010000000000 : out = 4'b1010; 
			16'b0000100000000000 : out = 4'b1011; 
			16'b0001000000000000 : out = 4'b1100; 
			16'b0010000000000000 : out = 4'b1101; 
			16'b0100000000000000 : out = 4'b1110; 
			16'b1000000000000000 : out = 4'b1111;
			default: out = 4'bxxxx; 
		endcase
		
	end


endmodule

PROGRAMS/verilog/COA/Assignment1/Assignment1COA-master/Q2/encoder/t_encoder.v
/**
*	Test bench for 16:4 encoder
*	By: Omkar Prabhu 16CO233
*	13th October 2017
*/

`timescale 1ns/100ps

module t_encoder;

	///output
	wire [0:3] out;
	// input
	reg [0:15] in;
	
	// encoder thread instantiated
	encoder inst (out, in);
	
	// check for various input combinations
	initial begin
	
		$dumpfile("encoder.vcd");
		$dumpvars(0, t_encoder);
		
		in = 16'b0000000000000001;
	
		#10
		in = 16'b0000000000000010;
		#10
		in = 16'b0000000000000100;
		#10
		in = 16'b0000000000000101;
		#10
		in = 16'b0000000000001000;
		#10
		in = 16'b0000000000010000;	
		#10
		in = 16'b0000000000100000;	
		#10
		in = 16'b0000000001000000;	
		#10
		in = 16'b0000000010000000;
		#10
		in = 16'b0000000011000000;		
		#10
		in = 16'b0000000100000000;	
		#10
		in = 16'b0000001000000000;	
		#10
		in = 16'b0000010000000000;	
		#10
		in = 16'b0000100000000000;	
		#10
		in = 16'b0001000000000000;	
		#10
		in = 16'b0010000000000000;	
		#10
		in = 16'b0100000000000000;	
		#10
		in = 16'b1000000000000000;
		#10;					
		
	end	
	
	// display meaning of input and output
	initial begin
		$display("\tinput: D15D14D13D12D11D10D9D8D7D6D5D4D3D2D1D0  output: E3E2E1E0");	
	end
	
	// print result
	initial begin
		$monitor("%t: input: %b output: %b", $time, in, out);	
	end
	
endmodule

PROGRAMS/verilog/COA/Assignment1/Assignment1COA-master/Q2/encoder/encoder.vcd
$date
	Mon Oct 16 15:07:22 2017
$end
$version
	Icarus Verilog
$end
$timescale
	100ps
$end
$scope module t_encoder $end
$var wire 4 ! out [0:3] $end
$var reg 16 " in [0:15] $end
$scope module inst $end
$var wire 16 # in [0:15] $end
$var reg 4 $ out [0:3] $end
$upscope $end
$upscope $end
$enddefinitions $end
#0
$dumpvars
b0 $
b1 #
b1 "
b0 !
$end
#100
b1 $
b1 !
b10 "
b10 #
#200
b10 $
b10 !
b100 "
b100 #
#300
bx $
bx !
b101 "
b101 #
#400
b11 $
b11 !
b1000 "
b1000 #
#500
b100 $
b100 !
b10000 "
b10000 #
#600
b101 $
b101 !
b100000 "
b100000 #
#700
b110 $
b110 !
b1000000 "
b1000000 #
#800
b111 $
b111 !
b10000000 "
b10000000 #
#900
bx $
bx !
b11000000 "
b11000000 #
#1000
b1000 $
b1000 !
b100000000 "
b100000000 #
#1100
b1001 $
b1001 !
b1000000000 "
b1000000000 #
#1200
b1010 $
b1010 !
b10000000000 "
b10000000000 #
#1300
b1011 $
b1011 !
b100000000000 "
b100000000000 #
#1400
b1100 $
b1100 !
b1000000000000 "
b1000000000000 #
#1500
b1101 $
b1101 !
b10000000000000 "
b10000000000000 #
#1600
b1110 $
b1110 !
b100000000000000 "
b100000000000000 #
#1700
b1111 $
b1111 !
b1000000000000000 "
b1000000000000000 #
